{
  "hash": "66f3707f",
  "configHash": "abc77f30",
  "lockfileHash": "263973e7",
  "browserHash": "054eac49",
  "optimized": {
    "react": {
      "src": "../../node_modules/react/index.js",
      "file": "react.js",
      "fileHash": "31e07b7a",
      "needsInterop": true
    },
    "react-dom": {
      "src": "../../node_modules/react-dom/index.js",
      "file": "react-dom.js",
      "fileHash": "8ab9b3d5",
      "needsInterop": true
    },
    "react/jsx-dev-runtime": {
      "src": "../../node_modules/react/jsx-dev-runtime.js",
      "file": "react_jsx-dev-runtime.js",
      "fileHash": "5c0fb907",
      "needsInterop": true
    },
    "react/jsx-runtime": {
      "src": "../../node_modules/react/jsx-runtime.js",
      "file": "react_jsx-runtime.js",
      "fileHash": "ecd334a2",
      "needsInterop": true
    },
    "@radix-ui/react-dialog": {
      "src": "../../node_modules/@radix-ui/react-dialog/dist/index.mjs",
      "file": "@radix-ui_react-dialog.js",
      "fileHash": "cf4d13e6",
      "needsInterop": false
    },
    "@radix-ui/react-label": {
      "src": "../../node_modules/@radix-ui/react-label/dist/index.mjs",
      "file": "@radix-ui_react-label.js",
      "fileHash": "32e90f1a",
      "needsInterop": false
    },
    "@radix-ui/react-select": {
      "src": "../../node_modules/@radix-ui/react-select/dist/index.mjs",
      "file": "@radix-ui_react-select.js",
      "fileHash": "23805c34",
      "needsInterop": false
    },
    "@radix-ui/react-slot": {
      "src": "../../node_modules/@radix-ui/react-slot/dist/index.mjs",
      "file": "@radix-ui_react-slot.js",
      "fileHash": "eded2de0",
      "needsInterop": false
    },
    "@reduxjs/toolkit": {
      "src": "../../node_modules/@reduxjs/toolkit/dist/redux-toolkit.modern.mjs",
      "file": "@reduxjs_toolkit.js",
      "fileHash": "f238ec01",
      "needsInterop": false
    },
    "@stripe/stripe-js": {
      "src": "../../node_modules/@stripe/stripe-js/lib/index.mjs",
      "file": "@stripe_stripe-js.js",
      "fileHash": "c4bdec8a",
      "needsInterop": false
    },
    "@tanstack/react-table": {
      "src": "../../node_modules/@tanstack/react-table/build/lib/index.mjs",
      "file": "@tanstack_react-table.js",
      "fileHash": "89396a04",
      "needsInterop": false
    },
    "axios": {
      "src": "../../node_modules/axios/index.js",
      "file": "axios.js",
      "fileHash": "dca7fd56",
      "needsInterop": false
    },
    "chart.js": {
      "src": "../../node_modules/chart.js/dist/chart.js",
      "file": "chart__js.js",
      "fileHash": "5efeed35",
      "needsInterop": false
    },
    "class-variance-authority": {
      "src": "../../node_modules/class-variance-authority/dist/index.mjs",
      "file": "class-variance-authority.js",
      "fileHash": "8e3f56cf",
      "needsInterop": false
    },
    "clsx": {
      "src": "../../node_modules/clsx/dist/clsx.mjs",
      "file": "clsx.js",
      "fileHash": "b59396a0",
      "needsInterop": false
    },
    "date-fns": {
      "src": "../../node_modules/date-fns/index.js",
      "file": "date-fns.js",
      "fileHash": "c0940f31",
      "needsInterop": false
    },
    "date-fns/locale": {
      "src": "../../node_modules/date-fns/locale.js",
      "file": "date-fns_locale.js",
      "fileHash": "45f2b054",
      "needsInterop": false
    },
    "framer-motion": {
      "src": "../../node_modules/framer-motion/dist/es/index.mjs",
      "file": "framer-motion.js",
      "fileHash": "55bc269e",
      "needsInterop": false
    },
    "jspdf": {
      "src": "../../node_modules/jspdf/dist/jspdf.es.min.js",
      "file": "jspdf.js",
      "fileHash": "4ce1393d",
      "needsInterop": false
    },
    "jspdf-autotable": {
      "src": "../../node_modules/jspdf-autotable/dist/jspdf.plugin.autotable.mjs",
      "file": "jspdf-autotable.js",
      "fileHash": "fe59b189",
      "needsInterop": false
    },
    "lodash": {
      "src": "../../node_modules/lodash/lodash.js",
      "file": "lodash.js",
      "fileHash": "c7119085",
      "needsInterop": true
    },
    "lucide-react": {
      "src": "../../node_modules/lucide-react/dist/esm/lucide-react.js",
      "file": "lucide-react.js",
      "fileHash": "fa3f6054",
      "needsInterop": false
    },
    "prop-types": {
      "src": "../../node_modules/prop-types/index.js",
      "file": "prop-types.js",
      "fileHash": "c65fc4c8",
      "needsInterop": true
    },
    "react-chartjs-2": {
      "src": "../../node_modules/react-chartjs-2/dist/index.js",
      "file": "react-chartjs-2.js",
      "fileHash": "2a766eb1",
      "needsInterop": false
    },
    "react-dom/client": {
      "src": "../../node_modules/react-dom/client.js",
      "file": "react-dom_client.js",
      "fileHash": "d8a86752",
      "needsInterop": true
    },
    "react-hook-form": {
      "src": "../../node_modules/react-hook-form/dist/index.esm.mjs",
      "file": "react-hook-form.js",
      "fileHash": "61d7f815",
      "needsInterop": false
    },
    "react-infinite-scroll-component": {
      "src": "../../node_modules/react-infinite-scroll-component/dist/index.es.js",
      "file": "react-infinite-scroll-component.js",
      "fileHash": "a92970c6",
      "needsInterop": false
    },
    "react-redux": {
      "src": "../../node_modules/react-redux/dist/react-redux.mjs",
      "file": "react-redux.js",
      "fileHash": "c8f7f713",
      "needsInterop": false
    },
    "react-select": {
      "src": "../../node_modules/react-select/dist/react-select.esm.js",
      "file": "react-select.js",
      "fileHash": "47b3cb91",
      "needsInterop": false
    },
    "react-type-animation": {
      "src": "../../node_modules/react-type-animation/dist/esm/index.es.js",
      "file": "react-type-animation.js",
      "fileHash": "3515908d",
      "needsInterop": false
    },
    "sweetalert2": {
      "src": "../../node_modules/sweetalert2/dist/sweetalert2.esm.all.js",
      "file": "sweetalert2.js",
      "fileHash": "15cb4055",
      "needsInterop": false
    },
    "tailwind-merge": {
      "src": "../../node_modules/tailwind-merge/dist/bundle-mjs.mjs",
      "file": "tailwind-merge.js",
      "fileHash": "5d7412e6",
      "needsInterop": false
    },
    "three": {
      "src": "../../node_modules/three/build/three.module.js",
      "file": "three.js",
      "fileHash": "5b012e7f",
      "needsInterop": false
    },
    "xlsx": {
      "src": "../../node_modules/xlsx/xlsx.mjs",
      "file": "xlsx.js",
      "fileHash": "a933f433",
      "needsInterop": false
    },
    "@radix-ui/react-tooltip": {
      "src": "../../node_modules/@radix-ui/react-tooltip/dist/index.mjs",
      "file": "@radix-ui_react-tooltip.js",
      "fileHash": "95fa413c",
      "needsInterop": false
    },
    "next-themes": {
      "src": "../../node_modules/next-themes/dist/index.mjs",
      "file": "next-themes.js",
      "fileHash": "0a9ed6bc",
      "needsInterop": false
    },
    "@radix-ui/react-dropdown-menu": {
      "src": "../../node_modules/@radix-ui/react-dropdown-menu/dist/index.mjs",
      "file": "@radix-ui_react-dropdown-menu.js",
      "fileHash": "c3f9ad55",
      "needsInterop": false
    },
    "@radix-ui/react-avatar": {
      "src": "../../node_modules/@radix-ui/react-avatar/dist/index.mjs",
      "file": "@radix-ui_react-avatar.js",
      "fileHash": "adf6c655",
      "needsInterop": false
    },
    "@radix-ui/react-tabs": {
      "src": "../../node_modules/@radix-ui/react-tabs/dist/index.mjs",
      "file": "@radix-ui_react-tabs.js",
      "fileHash": "9ea721dd",
      "needsInterop": false
    }
  },
  "chunks": {
    "purify.es-SG2IBLQR": {
      "file": "purify__es-SG2IBLQR.js"
    },
    "index.es-KS732ONC": {
      "file": "index__es-KS732ONC.js"
    },
    "html2canvas.esm-47NA6HJN": {
      "file": "html2canvas__esm-47NA6HJN.js"
    },
    "chunk-XG5IKD4O": {
      "file": "chunk-XG5IKD4O.js"
    },
    "chunk-EC4PBLXT": {
      "file": "chunk-EC4PBLXT.js"
    },
    "chunk-OCCWAI5Z": {
      "file": "chunk-OCCWAI5Z.js"
    },
    "chunk-2XU5YHAM": {
      "file": "chunk-2XU5YHAM.js"
    },
    "chunk-ZGG2XPR5": {
      "file": "chunk-ZGG2XPR5.js"
    },
    "chunk-SITVF2AJ": {
      "file": "chunk-SITVF2AJ.js"
    },
    "chunk-KDVGFZWC": {
      "file": "chunk-KDVGFZWC.js"
    },
    "chunk-K53JEYXF": {
      "file": "chunk-K53JEYXF.js"
    },
    "chunk-PDT7FBPD": {
      "file": "chunk-PDT7FBPD.js"
    },
    "chunk-K2IMWAWA": {
      "file": "chunk-K2IMWAWA.js"
    },
    "chunk-PQZK4XUK": {
      "file": "chunk-PQZK4XUK.js"
    },
    "chunk-BIDPXX6L": {
      "file": "chunk-BIDPXX6L.js"
    },
    "chunk-BXYT624V": {
      "file": "chunk-BXYT624V.js"
    },
    "chunk-4BNCNAVA": {
      "file": "chunk-4BNCNAVA.js"
    },
    "chunk-RBWEE65M": {
      "file": "chunk-RBWEE65M.js"
    },
    "chunk-5FSV32GE": {
      "file": "chunk-5FSV32GE.js"
    },
    "chunk-5ZSYC24Q": {
      "file": "chunk-5ZSYC24Q.js"
    },
    "chunk-GCVFS7YQ": {
      "file": "chunk-GCVFS7YQ.js"
    },
    "chunk-EKFKCRXB": {
      "file": "chunk-EKFKCRXB.js"
    },
    "chunk-TZUS373Z": {
      "file": "chunk-TZUS373Z.js"
    },
    "chunk-3RKDWLCG": {
      "file": "chunk-3RKDWLCG.js"
    },
    "chunk-J3XBGEQK": {
      "file": "chunk-J3XBGEQK.js"
    },
    "chunk-ULSRCYB6": {
      "file": "chunk-ULSRCYB6.js"
    },
    "chunk-G3PMV62Z": {
      "file": "chunk-G3PMV62Z.js"
    }
  }
}